ukv-0.12.1.dist-info/METADATA
ukv-0.12.1.dist-info/LICENSE
ukv-0.12.1.dist-info/RECORD
ukv-0.12.1.dist-info/WHEEL
ukv-0.12.1.dist-info/top_level.txt
ustore/libustore_embedded_leveldb.a
ustore/py.typed
ustore/leveldb.cpython-310-x86_64-linux-gnu.so
ustore/libustore_embedded_ucset.a
ustore/libfmt.a
ustore/rocksdb.cpython-310-x86_64-linux-gnu.so
ustore/libustore_flight_client.a
ustore/__init__.py
ustore/libleveldb.a
ustore/libustore_embedded_rocksdb.a
ustore/libsimdjson.a
ustore/librocksdb.a
ustore/ucset.cpython-310-x86_64-linux-gnu.so
ustore/flight_client.cpython-310-x86_64-linux-gnu.so
ustore/libyyjson.a
ustore/__pycache__/__init__.cpython-310.pyc
ustore/flight_client/__init__.pyi
ustore/rocksdb/__init__.pyi
ustore/ucset/__init__.pyi
ustore/leveldb/__init__.pyi
ukv./libarrow-fa7e9f9c.so.1000
ukv./libarrow_dataset-28d3d89a.so.1000
ukv./libarrow_python-d6e811f5.so.1000
ukv./libparquet-27a45011.so.1000
