Metadata-Version: 2.1
Name: ukv
Version: 0.12.1
Summary: Python bindings for Unum's UStore.
Home-page: https://github.com/unum-cloud/ustore
Author: Ashot Vardanian
Author-email: info@unum.cloud
License: Apache-2.0
Classifier: Development Status :: 5 - Production/Stable
Classifier: Natural Language :: English
Classifier: Intended Audience :: Developers
Classifier: Intended Audience :: Information Technology
Classifier: License :: OSI Approved :: Apache Software License
Classifier: Operating System :: Unix
Classifier: Operating System :: POSIX
Classifier: Operating System :: POSIX :: Linux
Classifier: Programming Language :: C
Classifier: Programming Language :: C++
Classifier: Programming Language :: Python :: Implementation :: CPython
Classifier: Programming Language :: Python :: 3 :: Only
Classifier: Programming Language :: Python :: 3.7
Classifier: Programming Language :: Python :: 3.8
Classifier: Programming Language :: Python :: 3.9
Classifier: Programming Language :: Python :: 3.10
Classifier: Topic :: Database
Classifier: Topic :: Database :: Database Engines/Servers
Classifier: Topic :: Database :: Front-Ends
Requires-Python: >=3.7
License-File: LICENSE
Requires-Dist: numpy (>=1.16)
Requires-Dist: pyarrow (<11,>=10.0.0)
Provides-Extra: test
Requires-Dist: pytest ; extra == 'test'
